makina/__init__.py
makina/__main__.py
makina/constants.py
makina/displays.py
makina/instructions.py
makina-0.1.0.dist-info/entry_points.txt
makina-0.1.0.dist-info/WHEEL
makina-0.1.0.dist-info/METADATA
makina-0.1.0.dist-info/RECORD
