Metadata-Version: 2.1
Name: makina
Version: 0.1.0
Summary: A 2d cell-based esoteric language
Author: Ginger
Requires-Python: >=3.8.0,<3.10
Classifier: Programming Language :: Python :: 3
Classifier: Programming Language :: Python :: 3.8
Classifier: Programming Language :: Python :: 3.9
Requires-Dist: numpy (>=1.22.2,<2.0.0)
